Workbook
Name COFINS: #REF!
Name CSLL: #REF!
Name DADO_RECEITA: " "
Name DADOS_RECEITAS: #REF!
Name DRE: DRE!$C$6:$G$59
Name IMPOSTOS_DRE: DRE!$F$49:$F$54
Name IRPJ: #REF!
Name IRPJEXTRA: #REF!
Name ISS: #REF!
Name PIS: #REF!

Sheet DRE
F6: 2023 | H6: 2024 | J6: 2025
C8: TIPO | D8: Unidade
C10: Receita Operacional Bruta | D10: R$ | F10: =SUMIFS('20234T'!H:H,'20234T'!F:F,"301") -> 14942000 | H10: =SUMIFS('20244T'!H:H,'20244T'!F:F,"3.01") -> 14349000 | J10: =SUMIFS('20254T'!H:H,'20254T'!F:F,"3.01") -> 12305000
C12: Deduções | D12: R$ | F12: =F14-F10 -> 0 | H12: =H14-H10 -> 0 | J12: =J14-J10 -> 0
C14: (=) Receita Líquida | D14: R$ | F14: =SUMIFS('20234T'!H:H,'20234T'!F:F,"301") -> 14942000 | H14: =SUMIFS('20244T'!H:H,'20244T'!F:F,"3.01") -> 14349000 | J14: =SUMIFS('20254T'!H:H,'20254T'!F:F,"3.01") -> 12305000
C15: % Receita Líquida | D15: % | F15: =F14/F14 -> 1 | H15: =H14/H14 -> 1 | J15: =J14/J14 -> 1
C17: CMV | D17: R$ | F17: =SUMIFS('20234T'!H:H,'20234T'!F:F,"302") -> -10586000 | H17: =SUMIFS('20244T'!H:H,'20244T'!F:F,"3.02") -> -9722000 | J17: =SUMIFS('20254T'!H:H,'20254T'!F:F,"3.02") -> -8981000
D18: % | F18: =F17/F14 -> -0.70847276 | H18: =H17/H14 -> -0.6775385 | J18: =J17/J14 -> -0.72986591
C20: (=) Lucro Bruto | D20: R$ | F20: =SUMIFS('20234T'!H:H,'20234T'!F:F,"303") -> 4356000 | H20: =SUMIFS('20244T'!H:H,'20244T'!F:F,"3.03") -> 4627000 | J20: =SUMIFS('20254T'!H:H,'20254T'!F:F,"3.03") -> 3324000
C21: % Lucro Bruto | D21: % | F21: =F20/F14 -> 0.29152724 | H21: =H20/H14 -> 0.3224615 | J21: =J20/J14 -> 0.27013409
C23: Despesas | D23: R$ | F23: =SUMIFS('20234T'!H:H,'20234T'!F:F,"304") -> -8534000 | H23: =SUMIFS('20244T'!H:H,'20244T'!F:F,"3.04") -> -3977000 | J23: =SUMIFS('20254T'!H:H,'20254T'!F:F,"3.04") -> -2993000
F24: =F23/F14 -> -0.57114175 | H24: =H23/H14 -> -0.27716217 | J24: =J23/J14 -> -0.24323446
C26: DESPESAS ADMINISTRATIVAS | F26: =SUMIFS('20234T'!H:H,'20234T'!F:F,"30402") -> -3180000 | H26: =SUMIFS('20244T'!H:H,'20244T'!F:F,"3.04.02") -> -2137000 | J26: =SUMIFS('20254T'!H:H,'20254T'!F:F,"3.04.02") -> -1462000
C29: (=) EBITDA | D29: R$ | F29: =F34-F32 -> -2804000 | H29: =H34-H32 -> 1660000 | J29: =J34-J32 -> 1139000
C30: % EBITDA | D30: % | F30: =F29/F14 -> -0.18765895 | H30: =H29/H14 -> 0.1156875 | J30: =J29/J14 -> 0.092563998
C32: Depreciação e Amortização | D32: R$ | F32: =-SUMIFS('20234T'!H:H,'20234T'!F:F,"6010103") -> -1374000 | H32: =-SUMIFS('20244T'!H:H,'20244T'!F:F,"6.01.01.03") -> -1010000 | J32: =-SUMIFS('20254T'!H:H,'20254T'!F:F,"6.01.01.03") -> -808000
C34: (=) EBIT | D34: R$ | F34: =SUMIFS('20234T'!H:H,'20234T'!F:F,"305") -> -4178000 | H34: =SUMIFS('20244T'!H:H,'20244T'!F:F,"3.05") -> 650000 | J34: =SUMIFS('20254T'!H:H,'20254T'!F:F,"3.05") -> 331000
C35: % EBIT | D35: % | F35: =F34/F14 -> -0.27961451 | H35: =H34/H14 -> 0.045299324 | J35: =J34/J14 -> 0.026899634
C37: Despesas Financeiras | D37: R$ | F37: =SUMIFS('20234T'!H:H,'20234T'!F:F,"30602") -> -4240000 | H37: =SUMIFS('20244T'!H:H,'20244T'!F:F,"3.06.02") -> -4378000 | J37: =SUMIFS('20254T'!H:H,'20254T'!F:F,"3.06.02") -> -1127000
D38: % | F38: =F37/F14 -> -0.28376389 | H38: =H37/H14 -> -0.30510837 | J38: =J37/J14 -> -0.091588785
C40: Receitas Financeiras | D40: R$ | F40: =SUMIFS('20234T'!H:H,'20234T'!F:F,"30601") -> 1384000 | H40: =SUMIFS('20244T'!H:H,'20244T'!F:F,"3.06.01") -> 16697000 | J40: =SUMIFS('20254T'!H:H,'20254T'!F:F,"3.06.01") -> 963000
D41: % | F41: =F40/F14 -> 0.092624816 | H41: =H40/H14 -> 1.1636351 | J41: =J40/J14 -> 0.07826087
C43: (=) EBT | D43: R$ | F43: =SUMIFS('20234T'!H:H,'20234T'!F:F,"307") -> -7034000 | H43: =SUMIFS('20244T'!H:H,'20244T'!F:F,"3.07") -> 12969000 | J43: =SUMIFS('20254T'!H:H,'20254T'!F:F,"3.07") -> 167000
C44: % EBT | D44: % | F44: =F43/F14 -> -0.47075358 | H44: =H43/H14 -> 0.90382605 | J44: =J43/J14 -> 0.013571719
C46: Impostos | D46: R$ | F46: =SUMIFS('20234T'!H:H,'20234T'!F:F,"308") -> 4762000 | H46: =SUMIFS('20244T'!H:H,'20244T'!F:F,"3.08") -> -4717000 | J46: =SUMIFS('20254T'!H:H,'20254T'!F:F,"3.08") -> -69000
D47: % | F47: =F46/F14 -> 0.31869897 | H47: =H46/H14 -> -0.32873371 | J47: =J46/J14 -> -0.0056074766
C49: IRPJ | F49: =SUMIFS('20234T'!H:H,'20234T'!F:F,"30801") -> -32000 | H49: =SUMIFS('20244T'!H:H,'20244T'!F:F,"3.08.01") -> -38000 | J49: =SUMIFS('20254T'!H:H,'20254T'!F:F,"3.08.01") -> -14000
C50: SIMPLES NACIONAL
C51: PARCELAMENTO DE IMPOSTO
C52: IMPOSTO ESTADUAL
C53: IOF
C54: CSLL | F54: =SUMIFS('20234T'!H:H,'20234T'!F:F,"30802") -> 4794000 | H54: =SUMIFS('20244T'!H:H,'20244T'!F:F,"3.08.02") -> -4679000 | J54: =SUMIFS('20254T'!H:H,'20254T'!F:F,"3.08.02") -> -55000
C56: (=) Lucro Líquido | D56: R$ | F56: =SUMIFS('20234T'!H:H,'20234T'!F:F,"311") -> -2272000 | H56: =SUMIFS('20244T'!H:H,'20244T'!F:F,"3.11") -> 8281000 | J56: =SUMIFS('20254T'!H:H,'20254T'!F:F,"3.11") -> -271000
C57: % Lucro Líquido | D57: % | F57: =F56/F14 -> -0.15205461 | H57: =H56/H14 -> 0.57711339 | J57: =J56/J14 -> -0.022023568

Sheet Indicadores
B2: Indicadores | C2: Sigla | D2: Fórmulas | F2: 2024 | G2: 2025
B3: Liquidez
B4: Capital Circulante Líquido | C4: CCL | D4: AC - PC | F4: =SUMIFS(_2024[valor],_2024[descricao],Estrutura!$C$6)-SUMIFS(_2024[valor],_2024[descricao],Estrutura!$F$6) -> 2696000 | G4: =SUMIFS(_2025[valor],_2025[descricao],Estrutura!C6)-SUMIFS(_2025[valor],_2025[descricao],Estrutura!F6) -> 3107000
B5: Liquidez Corrente | C5: LC | D5: AC/PC | F5: =SUMIFS(_2024[valor],_2024[conta],"1.01")/SUMIFS(_2024[valor],_2024[conta],"2.01") -> 1.6152442 | G5: =SUMIFS(_2025[valor],_2025[conta],"1.01")/SUMIFS(_2025[valor],_2025[conta],"2.01") -> 1.6661664
B6: Liquidez Seca | C6: LS | D6: (AC - EST - DA) /PC | F6: =(SUMIFS(_2024[valor],_2024[conta],"1.01")-SUMIFS(_2024[valor],_2024[conta],"1.01.04")-SUMIFS(_2024[valor],_2024[conta],"1.01.07"))/SUMIFS(_2024[valor],_2024[conta],"2.01") -> 1.1522136 | G6: =(SUMIFS(_2025[valor],_2025[conta],"1.01")-SUMIFS(_2025[valor],_2025[conta],"1.01.04")-SUMIFS(_2025[valor],_2025[conta],"1.01.07"))/SUMIFS(_2025[valor],_2025[conta],"2.01") -> 1.2341338
B7: Liquidez Absoluta | C7: LA | D7: DISPONIVEL /PC | F7: =SUMIFS(_2024[valor],_2024[conta],"1.01.01")/SUMIFS(_2024[valor],_2024[conta],"2.01") -> 0.25764491 | G7: =SUMIFS(_2025[valor],_2025[conta],"1.01.01")/SUMIFS(_2025[valor],_2025[conta],"2.01") -> 0.18846484
B8: Liquidez Geral | C8: LG | D8: AC + ARLP / PC +PNC | F8: =(SUMIFS(_2024[valor],_2024[conta],"1.01")+SUMIFS(_2024[valor],_2024[conta],"1.02.01"))/(SUMIFS(_2024[valor],_2024[conta],"2.01")+SUMIFS(_2024[valor],_2024[conta],"2.02")) -> 0.90740296 | G8: =(SUMIFS(_2025[valor],_2025[conta],"1.01")+SUMIFS(_2025[valor],_2025[conta],"1.02.01"))/(SUMIFS(_2025[valor],_2025[conta],"2.01")+SUMIFS(_2025[valor],_2025[conta],"2.02")) -> 1.0289817
B10: Atividade
B11: Prazo Médio de Estocagem | C11: PME | D11: (ESTOQUE MÉDIO/CMV)*360 | F11: =((SUMIFS(_2023[valor],_2023[conta],"1.01.04")+SUMIFS(_2024[valor],_2024[conta],"1.01.04"))/2/ABS(SUMIFS(_2024[valor],_2024[conta],"3.02")))*360 -> 35.159432 | G11: =((SUMIFS(_2024[valor],_2024[conta],"1.01.04")+SUMIFS(_2025[valor],_2025[conta],"1.01.04"))/2/ABS(SUMIFS(_2025[valor],_2025[conta],"3.02")))*360 -> 75.138626
B12: Giro de Estoque | C12: GE | D12: 360/PME | F12: =360/F11 -> 10.239073 | G12: =360/G11 -> 4.7911443
B13: Prazo Médio de Recebimento de Vendas | C13: PMRV | D13: (CLIENTES MÉDIO /RECEITA)*360 | F13: =((SUMIFS(_2023[valor],_2023[conta],"1.01.03.01")+SUMIFS(_2024[valor],_2024[conta],"1.01.03.01"))/2/SUMIFS(_2024[valor],_2024[conta],"3.01"))*360 -> 22.529793 | G13: =((SUMIFS(_2024[valor],_2024[conta],"1.01.03.01")+SUMIFS(_2025[valor],_2025[conta],"1.01.03.01"))/2/SUMIFS(_2025[valor],_2025[conta],"3.01"))*360 -> 47.731816
B14: Compras | C14: - | D14: ESTOQUE FINAL - ESTOQUE INICIAL + CMV | F14: =ABS(SUMIFS(_2024[valor],_2024[conta],"3.02"))+SUMIFS(_2024[valor],_2024[conta],"1.01.04")-SUMIFS(_2023[valor],_2023[conta],"1.01.04") -> 11621000 | G14: =ABS(SUMIFS(_2025[valor],_2025[conta],"3.02"))+SUMIFS(_2025[valor],_2025[conta],"1.01.04")-SUMIFS(_2024[valor],_2024[conta],"1.01.04") -> 8932000
B15: Prazo Médio de Pagamento de Fornecedores | C15: PMPF | D15: (FORNECEDORES MÉDIO/COMPRAS)*360 | F15: =((SUMIFS(_2023[valor],_2023[conta],"2.01.02")+SUMIFS(_2024[valor],_2024[conta],"2.01.02"))/2/F14)*360 -> 33.921349 | G15: =((SUMIFS(_2024[valor],_2024[conta],"2.01.02")+SUMIFS(_2025[valor],_2025[conta],"2.01.02"))/2/G14)*360 -> 93.728168
B16: Ciclo Operacional | C16: CO | D16: PME+PMRV | F16: =F11+F13 -> 57.689225 | G16: =G11+G13 -> 122.87044
B17: Ciclo Financeiro | C17: CF | D17: CO-PMPF | F17: =F16-F15 -> 23.767876 | G17: =G16-G15 -> 29.142274
B18: Ciclo Econômico | C18: CE | D18: PME | F18: =F11 -> 35.159432 | G18: =G11 -> 75.138626
B19: Ativo Circulante Financeiro | C19: ACF | D19: - | F19: =SUMIFS(_2024[valor],_2024[conta],"1.01.01")+SUMIFS(_2024[valor],_2024[conta],"1.01.02") -> 1150000 | G19: =SUMIFS(_2025[valor],_2025[conta],"1.01.01")+SUMIFS(_2025[valor],_2025[conta],"1.01.02") -> 1054000
B20: Ativo Circulante Operacional | C20: ACO | D20: - | F20: =SUMIFS(_2024[valor],_2024[conta],"1.01")-F19 -> 5928000 | G20: =SUMIFS(_2025[valor],_2025[conta],"1.01")-G19 -> 6717000
B21: Ativo Circulante | C21: AC | D21: ACF + ACO | F21: =SUM(F19:F20) -> 7078000 | G21: =SUM(G19:G20) -> 7771000
B22: Passivo Circulante Financeiro | C22: PCF | D22: - | F22: =SUMIFS(_2024[valor],_2024[conta],"2.01.04") -> 49000 | G22: =SUMIFS(_2025[valor],_2025[conta],"2.01.04") -> 0
B23: Passivo Circulante Operacional | C23: PCO | D23: - | F23: =SUMIFS(_2024[valor],_2024[conta],"2.01")-F22 -> 4333000 | G23: =SUMIFS(_2025[valor],_2025[conta],"2.01")-G22 -> 4664000
B24: Passivo Circulante | C24: PC | D24: PCF + PCO | F24: =SUM(F22:F23) -> 4382000 | G24: =SUM(G22:G23) -> 4664000
B26: Capital de Giro
B27: Saldo em Tesouraria | C27: ST | D27: CDG = AC - PC | F27: =F19-F22 -> 1101000 | G27: =G19-G22 -> 1054000
B28: Necessidade de Capital de Giro | C28: NCG | D28: ST = ACF - PCF | F28: =F20-F23 -> 1595000 | G28: =G20-G23 -> 2053000
B29: Capital de Giro Líquido | C29: CGL | D29: NCG = ACO - PCO | F29: =F21-F24 -> 2696000 | G29: =G21-G24 -> 3107000
B31: Endividamento
B32: Relação de Capitais (Passivo/PL) | C32: RCPT | D32: PASSIVO/PL | F32: =(SUMIFS(_2024[valor],_2024[conta],"2.01")+SUMIFS(_2024[valor],_2024[conta],"2.02"))/SUMIFS(_2024[valor],_2024[conta],"2.03") -> 2.5140845 | G32: =(SUMIFS(_2025[valor],_2025[conta],"2.01")+SUMIFS(_2025[valor],_2025[conta],"2.02"))/SUMIFS(_2025[valor],_2025[conta],"2.03") -> 2.4143728
B33: Endividamento Geral (Passivo/(Passivo + PL)) | C33: EG | D33: PASSIVO/PASSIVO+PL | F33: =(SUMIFS(_2024[valor],_2024[conta],"2.01")+SUMIFS(_2024[valor],_2024[conta],"2.02"))/(SUMIFS(_2024[valor],_2024[conta],"2.01")+SUMIFS(_2024[valor],_2024[conta],"2.02")+SUMIFS(_2024[valor],_2024[conta],"2.03")) -> 0.71543086 | G33: =(SUMIFS(_2025[valor],_2025[conta],"2.01")+SUMIFS(_2025[valor],_2025[conta],"2.02"))/(SUMIFS(_2025[valor],_2025[conta],"2.01")+SUMIFS(_2025[valor],_2025[conta],"2.02")+SUMIFS(_2025[valor],_2025[conta],"2.03")) -> 0.70712044
B34: Solvência Geral (Ativo/Passivo) | C34: SG | D34: ATIVO TOTAL/PASSIVO | F34: =SUMIFS(_2024[valor],_2024[conta],"1")/( SUMIFS(_2024[valor],_2024[conta],"2.01")+SUMIFS(_2024[valor],_2024[conta],"2.02")) -> 1.3977591 | G34: =SUMIFS(_2025[valor],_2025[conta],"1")/(SUMIFS(_2025[valor],_2025[conta],"2.01")+SUMIFS(_2025[valor],_2025[conta],"2.02")) -> 1.4141862
B35: Composição do Endividamento (PC/Passivo) | C35: CE | D35: PC/PASSIVO | F35: =SUMIFS(_2024[valor],_2024[conta],"2.01")/(SUMIFS(_2024[valor],_2024[conta],"2.01")+SUMIFS(_2024[valor],_2024[conta],"2.02")) -> 0.35070028 | G35: =SUMIFS(_2025[valor],_2025[conta],"2.01")/(SUMIFS(_2025[valor],_2025[conta],"2.01")+SUMIFS(_2025[valor],_2025[conta],"2.02")) -> 0.40591819
B36: Imobilização do PL (Ativos Fixos/PL) | C36: IPL | D36: ATIVOS FIXOS(3is)/PL | F36: =(SUMIFS(_2024[valor],_2024[conta],"1.02.02")+SUMIFS(_2024[valor],_2024[conta],"1.02.03")+SUMIFS(_2024[valor],_2024[conta],"1.02.04"))/SUMIFS(_2024[valor],_2024[conta],"2.03") -> 1.2327968 | G36: =(SUMIFS(_2025[valor],_2025[conta],"1.02.02")+SUMIFS(_2025[valor],_2025[conta],"1.02.03")+SUMIFS(_2025[valor],_2025[conta],"1.02.04"))/SUMIFS(_2025[valor],_2025[conta],"2.03") -> 0.93002732
B37: Passivo Oneroso | C37: PO | D37: PASSIVOS QUE GERAM DESPESAS FINANCEIRAS | F37: =SUMIFS(_2024[valor],_2024[conta],"2.01.04")+SUMIFS(_2024[valor],_2024[conta],"2.02.01") -> 1782000 | G37: =SUMIFS(_2025[valor],_2025[conta],"2.01.04")+SUMIFS(_2025[valor],_2025[conta],"2.02.01") -> 1995000
B38: Dívida Líquida | C38: DL | D38: PO - (DISPONÍVEL + AP. FINANCEIRA) | F38: =F37-(SUMIFS(_2024[valor],_2024[conta],"1.01.01")+SUMIFS(_2024[valor],_2024[conta],"1.01.02")) -> 632000 | G38: =G37-(SUMIFS(_2025[valor],_2025[conta],"1.01.01")+SUMIFS(_2025[valor],_2025[conta],"1.01.02")) -> 941000
B39: Investimento | C39: INV | D39: PO + PL | F39: =F37+SUMIFS(_2024[valor],_2024[conta],"2.03") -> 6752000 | G39: =G37+SUMIFS(_2025[valor],_2025[conta],"2.03") -> 6754000
B40: Capital Oneroso | C40: CO | D40: DÍVIDA LÍQUIDA + PL | F40: =F38+SUMIFS(_2024[valor],_2024[conta],"2.03") -> 5602000 | G40: =G38+SUMIFS(_2025[valor],_2025[conta],"2.03") -> 5700000
B41: Relação dívida Líquida - PL | C41: - | D41: DL/PL | F41: =F38/SUMIFS(_2024[valor],_2024[conta],"2.03") -> 0.12716298 | G41: =G38/SUMIFS(_2025[valor],_2025[conta],"2.03") -> 0.19773062
B42: Relação divida líquida e CO | C42: - | D42: DÍVIDA LÍQUIDA /dívida líquida + PL | F42: =F38/F40 -> 0.11281685 | G42: =G38/G40 -> 0.16508772
B44: Custo do Capital
B45: Percentual da Dívida no Investimento | C45: Wi | D45: PO/Investimento | F45: =F37/F39 -> 0.2639218 | G45: =G37/G39 -> 0.29538052
B46: Percentual da Equity no Investimento | C46: We | D46: PL/Investimento | F46: =SUMIFS(_2024[valor],_2024[conta],"2.03")/F39 -> 0.7360782 | G46: =SUMIFS(_2025[valor],_2025[conta],"2.03")/G39 -> 0.70461948
B47: Despesa Financeira Líquida | C47: DFL | D47: DF - BENEFÍCIO TRIBUTÁRIO | F47: =ABS(SUMIFS(_2024[valor],_2024[conta],"3.06.02"))-F48 -> 2785662.4 | G47: =ABS(SUMIFS(_2025[valor],_2025[conta],"3.06.02"))-G48 -> 661353.29
B48: Benefício Tributário da Dívida | C48: BT | D48: DESPESA FINANCEIRA X ALÍQUOTA IR/CSLL | F48: =ABS(SUMIFS(_2024[valor],_2024[conta],"3.06.02"))*F49 -> 1592337.6 | G48: =ABS(SUMIFS(_2025[valor],_2025[conta],"3.06.02"))*G49 -> 465646.71
B49: Aliquota Efetiva IR/CSLL | C49: % IR | D49: PROVISÃO IR/CSLL / LAIR | F49: =IFERROR(-SUMIFS(_2024[valor],_2024[conta],"3.08")/SUMIFS(_2024[valor],_2024[conta],"3.07"),0) -> 0.36371347 | G49: =IFERROR(-SUMIFS(_2025[valor],_2025[conta],"3.08")/SUMIFS(_2025[valor],_2025[conta],"3.07"),0) -> 0.41317365
B50: Custo da Dívida | C50: Ki | D50: Despesa financeira / PO | F50: =ABS(SUMIFS(_2024[valor],_2024[conta],"3.06.02"))/F37 -> 2.4567901 | G50: =ABS(SUMIFS(_2025[valor],_2025[conta],"3.06.02"))/G37 -> 0.56491228
B51: Custo Médio Ponderado de Capital | C51: CMPC | D51: Wi x Ki + We x Ke | F51: =F45*F50*(1-F49)+F46*0.15 -> 0.52298022 | G51: =G45*G50*(1-G49)+G46*0.15 -> 0.20361316
B53: Lucratividade e Rentabilidade
B54: Margem Bruta | C54: MB | D54: LUCRO BRUTO/RECEITA LÍQUIDA | F54: =SUMIFS(_2024[valor],_2024[conta],"3.03")/SUMIFS(_2024[valor],_2024[conta],"3.01") -> 0.3224615 | G54: =SUMIFS(_2025[valor],_2025[conta],"3.03")/SUMIFS(_2025[valor],_2025[conta],"3.01") -> 0.27013409
B55: EBITDA | C55: EBITDA | D55: LUCRO OPERACIONAL + DESPESAS D&A | F55: =SUMIFS(_2024[valor],_2024[conta],"3.05")+ABS(SUMIFS(_2024[valor],_2024[conta],"7.04.01")) -> 1660000 | G55: =SUMIFS(_2025[valor],_2025[conta],"3.05")+ABS(SUMIFS(_2025[valor],_2025[conta],"7.04.01")) -> 1139000
B56: Margem EBITDA | C56: % EBITDA | D56: EBITDA/RECEITA LÍQUIDA | F56: =F55/SUMIFS(_2024[valor],_2024[conta],"3.01") -> 0.1156875 | G56: =G55/SUMIFS(_2025[valor],_2025[conta],"3.01") -> 0.092563998
B57: EBIT | C57: EBIT | D57: LUCRO OPERACIONAL | F57: =SUMIFS(_2024[valor],_2024[conta],"3.05") -> 650000 | G57: =SUMIFS(_2025[valor],_2025[conta],"3.05") -> 331000
B58: Margem EBIT | C58: % EBIT | D58: EBIT/RECEITA LÍQUIDA | F58: =F57/SUMIFS(_2024[valor],_2024[conta],"3.01") -> 0.045299324 | G58: =G57/SUMIFS(_2025[valor],_2025[conta],"3.01") -> 0.026899634
B59: NOPAT | C59: NOPAT | D59: LUCRO OPERACIONAL - IR/CSLL | F59: =F57*(1-F49) -> 413586.24 | G59: =G57*(1-G49) -> 194239.52
B60: Margem NOPAT | C60: % NOPAT | D60: NOPAT/RECEITA LÍQUIDA | F60: =F59/SUMIFS(_2024[valor],_2024[conta],"3.01") -> 0.02882335 | G60: =G59/SUMIFS(_2025[valor],_2025[conta],"3.01") -> 0.015785414
B61: Margem Líquida | C61: ML | D61: LUCRO LÍQUIDO/RECEITA LÍQUIDA | F61: =SUMIFS(_2024[valor],_2024[conta],"3.11")/SUMIFS(_2024[valor],_2024[conta],"3.01") -> 0.57711339 | G61: =SUMIFS(_2025[valor],_2025[conta],"3.11")/SUMIFS(_2025[valor],_2025[conta],"3.01") -> -0.022023568
B62: Retorno sobre o Investimento | C62: ROI | D62: NOPAT/INVESTIMENTO | F62: =F59/F39 -> 0.061253887 | G62: =G59/G39 -> 0.028759183
B63: Retorno sobre o Equity (PL) | C63: ROE | D63: LUCRO LÍQUIDO / PL | F63: =SUMIFS(_2024[valor],_2024[conta],"3.11")/SUMIFS(_2024[valor],_2024[conta],"2.03") -> 1.6661972 | G63: =SUMIFS(_2025[valor],_2025[conta],"3.11")/SUMIFS(_2025[valor],_2025[conta],"2.03") -> -0.056944736
B64: Grau de Alavancagem Financeira | C64: GAF | D64: ROE/ROI | F64: =F63/F62 -> 27.201493 | G64: =G63/G62 -> -1.980054
B66: Valor Agregado
B67: Valor Econômico Adicionado | C67: EVA | D67: (ROI - CMPC) x Investimento | F67: =(F62-F51)*F39 -> -3117576.2 | G67: =(G62-G51)*G39 -> -1180963.8
B68: ROI Residual | C68: RROI | D68: ROI - CMPC | F68: =F62-F51 -> -0.46172633 | G68: =G62-G51 -> -0.17485398
B69: Goodwill | C69: - | D69: EVA/CMPC | F69: =IFERROR(F67/F51,"n/a") -> -5961174.2 | G69: =IFERROR(G67/G51,"n/a") -> -5800036.5
B71: Indicadores de Múltiplos
B72: Nº de ações | C72: - | D72: Achar no site do RI da empresa | F72: 200244252 | G72: 200244998
B73: Valor Patrimonial das Ações | C73: VPA | D73: PL / Número de Ações | F73: =IFERROR(SUMIFS(_2024[valor],_2024[conta],"2.03")*1000/F72,"-") -> 24.819689 | G73: =IFERROR(SUMIFS(_2025[valor],_2025[conta],"2.03")*1000/G72,"-") -> 23.765887
B74: Preço Atual da ação | C74: Preço | D74: Achar em sites tipos Investidor 10, Suno etc | F74: 6.2 | G74: 5.13
B75: Indicador Preço/Valor Patrimonial | C75: P/VP | D75: Preço/VPA | F75: =IFERROR(F74/F73,"-") -> 0.24980168 | G75: =IFERROR(G74/G73,"-") -> 0.21585561
B76: Price to book | C76: - | D76: Market cap/PL | F76: =IFERROR(F79/(SUMIFS(_2024[valor],_2024[conta],"2.03")*1000),"-") -> 0.24980168 | G76: =IFERROR(G79/(SUMIFS(_2025[valor],_2025[conta],"2.03")*1000),"-") -> 0.21585561
B77: Lucro por Ação | C77: LPA | D77: Lucro líquido/ Nº de ações | F77: =IFERROR(SUMIFS(_2024[valor],_2024[conta],"3.11")*1000/F72,"-") -> 41.354495 | G77: =IFERROR(SUMIFS(_2025[valor],_2025[conta],"3.11")*1000/G72,"-") -> -1.3533422
B78: Indicador Preço/Lucro | C78: P/L | D78: Valor da ação/LPA | F78: =IFERROR(F74/F77,"-") -> 0.14992324 | G78: =IFERROR(G74/G77,"-") -> -3.7906156
B79: Capitalização da Empresa | C79: Market cap | D79: Número de ações x preço da ação | F79: =IFERROR(F72*F74,"-") -> 1.2415144e+09 | G79: =IFERROR(G72*G74,"-") -> 1.0272568e+09
B80: Dividendos Totais Pagos | C80: DTP | D80: Ver na DFC
B81: Dividendos por Ação | C81: DPA | D81: Dividendos/Nº de ações | F81: =IFERROR(F80/F72,"-") -> 0 | G81: =IFERROR(G80/G72,"-") -> 0
B82: Dividend Yield | C82: DY | D82: DPA/preço atual da ação | F82: =IFERROR(F81/F74,"-") -> 0 | G82: =IFERROR(G81/G74,"-") -> 0
B83: Payout | C83: Payout | D83: DPA/LPA | F83: =IFERROR(F81/F77,"-") -> 0 | G83: =IFERROR(G81/G77,"-") -> 0
B84: Ganho de Capital com ações | C84: Δ Preço | D84: Preço atual da ação - Preço que eu paguei pela ação (Δ Início e fim de 2025) | F84: =IFERROR(F74-#REF!,"-") -> - | G84: =IFERROR(G74-F74,"-") -> -1.07
B85: Retorno com Ganhos de Capital | C85: - | D85: Δ Preço / Preço que eu paguei pela ação (Preço início de 2024) | F85: =IFERROR(F84/#REF!,"-") -> - | G85: =IFERROR(G84/F74,"-") -> -0.17258065
B86: Taxa de Retorno Total da Ação | C86: TRA | D86: (DPA+ Δ Preço)/Preço que eu paguei pela ação (Preço início de 2024) | F86: =IFERROR((F81+F84)/#REF!,"-") -> - | G86: =IFERROR((G81+G84)/F74,"-") -> -0.17258065
B87: Entrerprise Value (Valor da Firma) | C87: EV | D87: Market cap + Dívida Líquida | F87: =IFERROR(F79+F38,"-") -> 1.2421464e+09 | G87: =IFERROR(G79+G38,"-") -> 1.0281978e+09
B88: EV/Ebitda | C88: - | D88: EV/Ebitda | F88: =IFERROR(F87/(F55*1000),"-") -> 0.74828094 | G88: =IFERROR(G87/(G55*1000),"-") -> 0.90271979
B89: EV/Receita | C89: - | D89: EV/Receita | F89: =IFERROR(F87/(SUMIFS(_2024[valor],_2024[conta],"3.01")*1000),"-") -> 0.086566755 | G89: =IFERROR(G87/(SUMIFS(_2025[valor],_2025[conta],"3.01")*1000),"-") -> 0.083559353
B90: Earning Yield | C90: EY | D90: Ebitda/EV | F90: =IFERROR((F55*1000)/F87,"-") -> 1.3363965 | G90: =IFERROR((G55*1000)/G87,"-") -> 1.1077635

Sheet Estrutura
B3: Ativo | E3: Passivo | H3: DRE | K3: Fluxo de Caixa (FC)
B4: Conta | C4: Descricao | E4: Conta | F4: Descricao | H4: Conta | I4: Descricao | K4: Conta | L4: Descricao | N4: Conta | O4: Descricao
B5: 1 | C5: Ativo Total | E5: 2 | F5: Passivo Total | H5: 3.01 | I5: Receita de Venda de Bens e/ou Serviços | K5: 6.01 | L5: Caixa Líquido Atividades Operacionais | N5: 7.01 | O5: Receitas
B6: 1.01 | C6: Ativo Circulante | E6: 2.01 | F6: Passivo Circulante | H6: 3.02 | I6: Custo dos Bens e/ou Serviços Vendidos | K6: 6.01.01 | L6: Caixa Gerado nas Operações | N6: 7.01.01 | O6: Vendas de Mercadorias, Produtos e Serviços
B7: 1.01.01 | C7: Caixa e Equivalentes de Caixa | E7: 2.01.01 | F7: Obrigações Sociais e Trabalhistas | H7: 3.03 | I7: Resultado Bruto | K7: 6.01.01.01 | L7: Lucro do exercício das operações continuadas | N7: 7.01.02 | O7: Outras Receitas
B8: 1.01.02 | C8: Aplicações Financeiras | E8: 2.01.01.01 | F8: Obrigações Sociais | H8: 3.04 | I8: Despesas/Receitas Operacionais | K8: 6.01.01.02 | L8: Prejuízo do exercício das operações descontinuadas | N8: 7.01.03 | O8: Receitas refs. à Construção de Ativos Próprios
B9: 1.01.02.01 | C9: Aplicações Financeiras Avaliadas a Valor Justo através do Resultado | E9: 2.01.01.02 | F9: Obrigações Trabalhistas | H9: 3.04.01 | I9: Despesas com Vendas | K9: 6.01.01.03 | L9: Depreciação e amortização | N9: 7.01.04 | O9: Provisão/Reversão de Créds. Liquidação Duvidosa
B10: 1.01.02.01.01 | C10: Títulos para Negociação | E10: 2.01.01.02.01 | F10: Salários, encargos e contribuições | H10: 3.04.02 | I10: Despesas Gerais e Administrativas | K10: 6.01.01.04 | L10: Imposto de renda e contribuição social corrente e diferido | N10: 7.02 | O10: Insumos Adquiridos de Terceiros
B11: 1.01.02.01.02 | C11: Títulos Designados a Valor Justo | E11: 2.01.02 | F11: Fornecedores | H11: 3.04.03 | I11: Perdas pela Não Recuperabilidade de Ativos | K11: 6.01.01.05 | L11: Juros, variações monetárias, cambiais e custo de captação | N11: 7.02.01 | O11: Custos Prods., Mercs. e Servs. Vendidos
B12: 1.01.02.01.03 | C12: Títulos e valores mobiliários | E12: 2.01.02.01 | F12: Fornecedores Nacionais | H12: 3.04.04 | I12: Outras Receitas Operacionais | K12: 6.01.01.06 | L12: Equivalência patrimonial | N12: 7.02.02 | O12: Materiais, Energia, Servs. de Terceiros e Outros
B13: 1.01.02.01.04 | C13: Outros ativos financeiros | E13: 2.01.02.01.01 | F13: Fornecedores Nacionais | H13: 3.04.05 | I13: Outras Despesas Operacionais | K13: 6.01.01.07 | L13: Constituição de provisão para processos judiciais e contingências | N13: 7.02.03 | O13: Perda/Recuperação de Valores Ativos
B14: 1.01.02.02 | C14: Aplicações Financeiras Avaliadas a Valor Justo através de Outros Resultados Abrangentes | E14: 2.01.02.02 | F14: Fornecedores Estrangeiros | H14: 3.04.05.02 | I14: Honorários Administradores | K14: 6.01.01.08 | L14: Reversão de provisão para processos judiciais e contingências | N14: 7.02.04 | O14: Outros
B15: 1.01.02.03 | C15: Aplicações Financeiras Avaliadas ao Custo Amortizado | E15: 2.01.03 | F15: Obrigações Fiscais | H15: 3.04.05.03 | I15: Outras (despesas) receitas operacionais | K15: 6.01.01.09 | L15: Ajuste a valor presente de obrigações | N15: 7.03 | O15: Valor Adicionado Bruto
... B36: 1.02.01.01 | C36: Aplicações Financeiras Avaliadas a Valor Justo através do Resultado | E36: 2.01.05.01 | F36: Passivos com Partes Relacionadas | H36: 3.99.02.01 | I36: ON | K36: 6.01.02.18 | L36: Atividades operacionais - operações descontinuadas | N36: 7.08.03 | O36: Remuneração de Capitais de Terceiros
B37: 1.02.01.01.01 | C37: Títulos Designados a Valor Justo | E37: 2.01.05.01.01 | F37: Débitos com Coligadas | K37: 6.01.03 | L37: Outros | N37: 7.08.03.01 | O37: Juros
B38: 1.02.01.02 | C38: Aplicações Financeiras Avaliadas a Valor Justo através de Outros Resultados Abrangentes | E38: 2.01.05.01.03 | F38: Débitos com Controladores | K38: 6.02 | L38: Caixa Líquido Atividades de Investimento | N38: 7.08.03.02 | O38: Aluguéis
B39: 1.02.01.03 | C39: Aplicações Financeiras Avaliadas ao Custo Amortizado | E39: 2.01.05.01.04 | F39: Débitos com Outras Partes Relacionadas | K39: 6.02.01 | L39: Títulos e valores mobiliários e FIDC | N39: 7.08.03.03 | O39: Outras
B40: 1.02.01.03.01 | C40: Clientes | E40: 2.01.05.02 | F40: Outros | K40: 6.02.02 | L40: Aquisição de imobilizado e intangível | N40: 7.08.04 | O40: Remuneração de Capitais Próprios
B41: 1.02.01.03.02 | C41: Outras Contas a Receber | E41: 2.01.05.02.01 | F41: Dividendos e JCP a Pagar | K41: 6.02.03 | L41: Aumento de capital em controladas | N41: 7.08.04.01 | O41: Juros sobre o Capital Próprio
B42: 1.02.01.04 | C42: Contas a Receber | E42: 2.01.05.02.02 | F42: Dividendo Mínimo Obrigatório a Pagar | K42: 6.02.04 | L42: Caixa líquido incorporado | N42: 7.08.04.02 | O42: Dividendos
B43: 1.02.01.04.01 | C43: Clientes | E43: 2.01.05.02.03 | F43: Obrigações por Pagamentos Baseados em Ações | K43: 6.02.06 | L43: Valor pago pelas aquisições de controladas | N43: 7.08.04.03 | O43: Lucros Retidos / Prejuízo do Período
B44: 1.02.01.04.02 | C44: Outras Contas a Receber | E44: 2.01.05.02.04 | F44: Outras Obrigações | K44: 6.02.07 | L44: Valor recebido pela venda de controladas | N44: 7.08.04.04 | O44: Part. Não Controladores nos Lucros Retidos
B45: 1.02.01.05 | C45: Estoques | E45: 2.01.05.02.05 | F45: Contas a Pagar - Combinação de Negócios | K45: 6.02.08 | L45: Aumento de capital em controladas | N45: 7.08.05 | O45: Outros
B46: 1.02.01.05.03 | C46: Depósitos Judiciais | E46: 2.01.05.02.06 | F46: Adiantamento Recebido de Clientes | K46: 6.02.09 | L46: Aquisições de participações societárias | N46: 7.08.05.01 | O46: Resultado das operações descontinuadas
B47: 1.02.01.05.04 | C47: Impostos a recuperar | E47: 2.01.05.02.07 | F47: Passivo de arrendamento | K47: 6.02.10 | L47: Dividendos recebidos
B48: 1.02.01.05.05 | C48: Outros Ativos Não Circulantes | E48: 2.01.05.02.08 | F48: Dividendos e participações propostos | K48: 6.02.11 | L48: Atividade de financiamento das operações descontinuadas
B49: 1.02.01.06 | C49: Ativos Biológicos | E49: 2.01.05.02.09 | F49: Risco Sacado | K49: 6.03 | L49: Caixa Líquido Atividades de Financiamento
B50: 1.02.01.07 | C50: Tributos Diferidos | E50: 2.01.06 | F50: Provisões | K50: 6.03.01 | L50: Captações de debêntures e empréstimos
B51: 1.02.01.07.01 | C51: Imposto de Renda e Contribuição Social Diferidos | E51: 2.01.06.01 | F51: Provisões Fiscais Previdenciárias Trabalhistas e Cíveis | K51: 6.03.02 | L51: Liquidações de debêntures e empréstimos
B52: 1.02.01.08 | C52: Despesas Antecipadas | E52: 2.01.06.01.01 | F52: Provisões Fiscais | K52: 6.03.03 | L52: Risco Sacado
B53: 1.02.01.09 | C53: Créditos com Partes Relacionadas | E53: 2.01.06.01.02 | F53: Provisões Previdenciárias e Trabalhistas | K53: 6.03.04 | L53: Pagamentos de passivo de arrendamento
B54: 1.02.01.09.01 | C54: Créditos com Coligadas | E54: 2.01.06.01.03 | F54: Provisões para Benefícios a Empregados | K54: 6.03.05 | L54: Aumento de capital
B55: 1.02.01.09.03 | C55: Créditos com Controladores | E55: 2.01.06.01.04 | F55: Provisões Cíveis | K55: 6.03.06 | L55: Reserva de Capital
B56: 1.02.01.09.04 | C56: Créditos com Outras Partes Relacionadas | E56: 2.01.06.01.05 | F56: Provisões Imobiliário | K56: 6.03.07 | L56: Dividendos
B57: 1.02.01.09.05 | C57: Contas a receber de acionistas - Plano de subscrição de ações | E57: 2.01.06.02 | F57: Outras Provisões | K57: 6.03.08 | L57: Pagamentos de passivo de arrendamento
B58: 1.02.01.10 | C58: Outros Ativos Não Circulantes | E58: 2.01.06.02.01 | F58: Provisões para Garantias | K58: 6.03.09 | L58: Ajuste de Avaliação patrimonial
... B66: 1.02.02 | C66: Investimentos | E66: 2.02.01.01 | F66: Empréstimos e Financiamentos | K66: 6.05.02 | L66: Saldo Final de Caixa e Equivalentes
B67: 1.02.02.01 | C67: Participações Societárias | E67: 2.02.01.01.01 | F67: Em Moeda Nacional
B68: 1.02.02.01.01 | C68: Participações em Coligadas | E68: 2.02.01.01.02 | F68: Em Moeda Estrangeira
B69: 1.02.02.01.04 | C69: Participações em Controladas em Conjunto | E69: 2.02.01.02 | F69: Debêntures
B70: 1.02.02.01.05 | C70: Outros Investimentos | E70: 2.02.01.02.01 | F70: Debêntures
B71: 1.02.02.02 | C71: Propriedades para Investimento | E71: 2.02.01.03 | F71: Financiamento por Arrendamento
B72: 1.02.03 | C72: Imobilizado | E72: 2.02.02 | F72: Outras Obrigações
B73: 1.02.03.01 | C73: Imobilizado em Operação | E73: 2.02.02.01 | F73: Passivos com Partes Relacionadas
B74: 1.02.03.02 | C74: Direito de Uso em Arrendamento | E74: 2.02.02.01.01 | F74: Débitos com Coligadas
B75: 1.02.03.02.01 | C75: Ativo de Direito de Uso | E75: 2.02.02.01.03 | F75: Débitos com Controladores
B76: 1.02.03.03 | C76: Imobilizado em Andamento | E76: 2.02.02.01.04 | F76: Débitos com Outras Partes Relacionadas
B77: 1.02.04 | C77: Intangível | E77: 2.02.02.02 | F77: Outros
B78: 1.02.04.01 | C78: Intangíveis | E78: 2.02.02.02.01 | F78: Obrigações por Pagamentos Baseados em Ações
... B80: 1.02.04.02 | C80: Goodwill | E80: 2.02.02.02.03 | F80: Outras Obrigações
E81: 2.02.02.02.04 | F81: Contas a Pagar - Combinação de Negócios
E82: 2.02.02.02.05 | F82: Passivo de arrendamento
E83: 2.02.02.02.06 | F83: Provisão para perdas em investimentos
E84: 2.02.02.02.07 | F84: Plano de Assistência Médica
E85: 2.02.02.02.08 | F85: Tributos a recolher
E86: 2.02.02.02.09 | F86: Fornecedores
E87: 2.02.03 | F87: Tributos Diferidos
E88: 2.02.03.01 | F88: Imposto de Renda e Contribuição Social Diferidos
E89: 2.02.04 | F89: Provisões
E90: 2.02.04.01 | F90: Provisões Fiscais Previdenciárias Trabalhistas e Cíveis
E91: 2.02.04.01.01 | F91: Provisões Fiscais
E92: 2.02.04.01.02 | F92: Provisões Previdenciárias e Trabalhistas
... E135: 2.03.09 | F135: Participação dos Acionistas Não Controladores

Sheet 20234T
A1: id | B1: empresa_tic | C1: ano_tri | D1: data_ini | E1: data_fim | F1: conta | G1: descricao | H1: valor | I1: tipo_balanco
A2: 5996616 | B2: AMER | C2: 20234T | D2: 45291 | E2: 45291 | F2: 1 | G2: Ativo Total | H2: 27115000 | I2: DFs Consolidadas
A3: 5996617 | B3: AMER | C3: 20234T | D3: 45291 | E3: 45291 | F3: 101 | G3: Ativo Circulante | H3: 10727000 | I3: DFs Consolidadas
A4: 5996618 | B4: AMER | C4: 20234T | D4: 45291 | E4: 45291 | F4: 10101 | G4: Caixa e Equivalentes de Caixa | H4: 1758000 | I4: DFs Consolidadas
A5: 5996619 | B5: AMER | C5: 20234T | D5: 45291 | E5: 45291 | F5: 10102 | G5: Aplicações Financeiras | H5: 2245000 | I5: DFs Consolidadas
A6: 5996620 | B6: AMER | C6: 20234T | D6: 45291 | E6: 45291 | F6: 1010201 | G6: Aplicações Financeiras Avaliadas a Valor Justo através do Resultado | H6: 2245000 | I6: DFs Consolidadas
A7: 5996621 | B7: AMER | C7: 20234T | D7: 45291 | E7: 45291 | F7: 101020101 | G7: Títulos para Negociação | H7: 0 | I7: DFs Consolidadas
A8: 5996622 | B8: AMER | C8: 20234T | D8: 45291 | E8: 45291 | F8: 101020102 | G8: Títulos Designados a Valor Justo | H8: 0 | I8: DFs Consolidadas
A9: 5996623 | B9: AMER | C9: 20234T | D9: 45291 | E9: 45291 | F9: 101020103 | G9: Títulos e valores mobiliários | H9: 2245000 | I9: DFs Consolidadas
A10: 5996624 | B10: AMER | C10: 20234T | D10: 45291 | E10: 45291 | F10: 101020104 | G10: Outros ativos financeiros | H10: 0 | I10: DFs Consolidadas
A11: 5996625 | B11: AMER | C11: 20234T | D11: 45291 | E11: 45291 | F11: 1010202 | G11: Aplicações Financeiras Avaliadas a Valor Justo através de Outros Resultados Abrangentes | H11: 0 | I11: DFs Consolidadas
A12: 5996626 | B12: AMER | C12: 20234T | D12: 45291 | E12: 45291 | F12: 1010203 | G12: Aplicações Financeiras Avaliadas ao Custo Amortizado | H12: 0 | I12: DFs Consolidadas
A13: 5996627 | B13: AMER | C13: 20234T | D13: 45291 | E13: 45291 | F13: 10103 | G13: Contas a Receber | H13: 2380000 | I13: DFs Consolidadas
... A337: 5996951 | B337: AMER | C337: 20234T | D337: 44927 | E337: 45291 | F337: 70805 | G337: Outros | H337: 0 | I337: DFs Consolidadas

Sheet 20244T
A1: id | B1: empresa_tic | C1: ano_tri | D1: data_ini | E1: data_fim | F1: conta | G1: descricao | H1: valor | I1: tipo_balanco
A2: 6169170 | B2: AMER | C2: 20244T | D2: 45657 | E2: 45657 | F2: 1 | G2: Ativo Total | H2: 17465000 | I2: DFs Consolidadas
A3: 6169171 | B3: AMER | C3: 20244T | D3: 45657 | E3: 45657 | F3: 1.01 | G3: Ativo Circulante | H3: 7078000 | I3: DFs Consolidadas
A4: 6169172 | B4: AMER | C4: 20244T | D4: 45657 | E4: 45657 | F4: 1.01.01 | G4: Caixa e Equivalentes de Caixa | H4: 1129000 | I4: DFs Consolidadas
A5: 6169173 | B5: AMER | C5: 20244T | D5: 45657 | E5: 45657 | F5: 1.01.02 | G5: Aplicações Financeiras | H5: 21000 | I5: DFs Consolidadas
A6: 6169174 | B6: AMER | C6: 20244T | D6: 45657 | E6: 45657 | F6: 1.01.02.01 | G6: Aplicações Financeiras Avaliadas a Valor Justo através do Resultado | H6: 21000 | I6: DFs Consolidadas
A7: 6169175 | B7: AMER | C7: 20244T | D7: 45657 | E7: 45657 | F7: 1.01.02.01.01 | G7: Títulos para Negociação | H7: 0 | I7: DFs Consolidadas
A8: 6169176 | B8: AMER | C8: 20244T | D8: 45657 | E8: 45657 | F8: 1.01.02.01.02 | G8: Títulos Designados a Valor Justo | H8: 0 | I8: DFs Consolidadas
A9: 6169177 | B9: AMER | C9: 20244T | D9: 45657 | E9: 45657 | F9: 1.01.02.01.03 | G9: Títulos e valores mobiliários | H9: 21000 | I9: DFs Consolidadas
A10: 6169178 | B10: AMER | C10: 20244T | D10: 45657 | E10: 45657 | F10: 1.01.02.01.04 | G10: Outros ativos financeiros | H10: 0 | I10: DFs Consolidadas
A11: 6169179 | B11: AMER | C11: 20244T | D11: 45657 | E11: 45657 | F11: 1.01.02.02 | G11: Aplicações Financeiras Avaliadas a Valor Justo através de Outros Resultados Abrangentes | H11: 0 | I11: DFs Consolidadas
A12: 6169180 | B12: AMER | C12: 20244T | D12: 45657 | E12: 45657 | F12: 1.01.02.03 | G12: Aplicações Financeiras Avaliadas ao Custo Amortizado | H12: 0 | I12: DFs Consolidadas
A13: 6169181 | B13: AMER | C13: 20244T | D13: 45657 | E13: 45657 | F13: 1.01.03 | G13: Contas a Receber | H13: 1796000 | I13: DFs Consolidadas
... A343: 6169511 | B343: AMER | C343: 20244T | D343: 45292 | E343: 45657 | F343: 7.08.05.01 | G343: Resultado das operações descontinuadas | H343: 29000 | I343: DFs Consolidadas

Sheet 20254T
A1: id | B1: empresa_tic | C1: ano_tri | D1: data_ini | E1: data_fim | F1: conta | G1: descricao | H1: valor | I1: tipo_balanco
A2: 6579475 | B2: AMER | C2: 20254T | D2: 46022 | E2: 46022 | F2: 1 | G2: Ativo Total | H2: 16249000 | I2: DFs Consolidadas
A3: 6579476 | B3: AMER | C3: 20254T | D3: 46022 | E3: 46022 | F3: 1.01 | G3: Ativo Circulante | H3: 7771000 | I3: DFs Consolidadas
A4: 6579477 | B4: AMER | C4: 20254T | D4: 46022 | E4: 46022 | F4: 1.01.01 | G4: Caixa e Equivalentes de Caixa | H4: 879000 | I4: DFs Consolidadas
A5: 6579478 | B5: AMER | C5: 20254T | D5: 46022 | E5: 46022 | F5: 1.01.02 | G5: Aplicações Financeiras | H5: 175000 | I5: DFs Consolidadas
A6: 6579479 | B6: AMER | C6: 20254T | D6: 46022 | E6: 46022 | F6: 1.01.02.01 | G6: Aplicações Financeiras Avaliadas a Valor Justo através do Resultado | H6: 175000 | I6: DFs Consolidadas
A7: 6579480 | B7: AMER | C7: 20254T | D7: 46022 | E7: 46022 | F7: 1.01.02.01.01 | G7: Títulos para Negociação | H7: 0 | I7: DFs Consolidadas
A8: 6579481 | B8: AMER | C8: 20254T | D8: 46022 | E8: 46022 | F8: 1.01.02.01.02 | G8: Títulos Designados a Valor Justo | H8: 0 | I8: DFs Consolidadas
A9: 6579482 | B9: AMER | C9: 20254T | D9: 46022 | E9: 46022 | F9: 1.01.02.01.03 | G9: Títulos e valores mobiliários | H9: 175000 | I9: DFs Consolidadas
A10: 6579483 | B10: AMER | C10: 20254T | D10: 46022 | E10: 46022 | F10: 1.01.02.01.04 | G10: Outros ativos financeiros | H10: 0 | I10: DFs Consolidadas
A11: 6579484 | B11: AMER | C11: 20254T | D11: 46022 | E11: 46022 | F11: 1.01.02.02 | G11: Aplicações Financeiras Avaliadas a Valor Justo através de Outros Resultados Abrangentes | H11: 0 | I11: DFs Consolidadas
A12: 6579485 | B12: AMER | C12: 20254T | D12: 46022 | E12: 46022 | F12: 1.01.02.03 | G12: Aplicações Financeiras Avaliadas ao Custo Amortizado | H12: 0 | I12: DFs Consolidadas
A13: 6579486 | B13: AMER | C13: 20254T | D13: 46022 | E13: 46022 | F13: 1.01.03 | G13: Contas a Receber | H13: 1467000 | I13: DFs Consolidadas
... A344: 6579817 | B344: AMER | C344: 20254T | D344: 45658 | E344: 46022 | F344: 7.08.05.01 | G344: Resultado das operações descontinuadas | H344: -369000 | I344: DFs Consolidadas
